Metadata-Version: 2.1
Name: monkeytype.py
Version: 1.0rc1
Summary: 🔧 A python wrapper built around the Monkeytype API.
Home-page: https://github.com/m2ksims/monkeytype.py
Author: Maksims K.
Author-email: contact@maksims.co.uk
License: MIT License
Classifier: Programming Language :: Python :: 3
Classifier: License :: OSI Approved :: MIT License
Classifier: Operating System :: OS Independent
Requires-Python: >=3.9
License-File: LICENSE
Requires-Dist: requests>=2.2.0
Requires-Dist: ratelimit>=2.2.1
